construe/__init__.py
construe/__main__.py
construe/basic.py
construe/exceptions.py
construe/gliner.py
construe/lowlight.py
construe/mobilenet.py
construe/mobilevit.py
construe/moondream.py
construe/nsfw.py
construe/offensive.py
construe/utils.py
construe/version.py
construe/whisper.py
construe/benchmark/__init__.py
construe/benchmark/base.py
construe/benchmark/limit.py
construe/benchmark/runner.py
construe/cloud/__init__.py
construe/cloud/download.py
construe/cloud/gcp.py
construe/cloud/manifest.py
construe/cloud/signature.py
construe/datasets/__init__.py
construe/datasets/__main__.py
construe/datasets/download.py
construe/datasets/loaders.py
construe/datasets/manifest.json
construe/datasets/manifest.py
construe/datasets/path.py
construe/datasets/source.py
construe/datasets/upload.py
construe/metrics/__init__.py
construe/metrics/metrics.py
construe/metrics/serialize.py
construe/models/__init__.py
construe/models/__main__.py
construe/models/convert.py
construe/models/download.py
construe/models/loaders.py
construe/models/manifest.json
construe/models/manifest.py
construe/models/path.py
construe/models/source.py
construe/models/tflite.py
construe/models/upload.py
construe-0.4.0.dist-info/LICENSE
construe-0.4.0.dist-info/METADATA
construe-0.4.0.dist-info/WHEEL
construe-0.4.0.dist-info/entry_points.txt
construe-0.4.0.dist-info/top_level.txt
construe-0.4.0.dist-info/RECORD
