Metadata-Version: 2.2
Name: construe
Version: 0.4.0
Summary: An LLM inferencing benchmark tool focusing on device-specific latency and memory usage
Download-URL: https://github.com/rotationalio/llm-benchmark/tarball/v0.4.0
Author: Rotational Labs
Author-email: support@rotational.io
Maintainer: Rotational Labs
Maintainer-email: support@rotational.io
License: BSD 3
Project-URL: Download, https://github.com/rotationalio/llm-benchmark/tarball/v0.4.0
Project-URL: Source, https://github.com/rotationalio/llm-benchmark
Project-URL: Tracker, https://github.com/rotationalio/llm-benchmark/issues
Keywords: llm,benchmark,construe,inference latency,inference memory
Classifier: Development Status :: 3 - Alpha
Classifier: Intended Audience :: Developers
Classifier: Intended Audience :: System Administrators
Classifier: License :: OSI Approved :: BSD License
Classifier: Natural Language :: English
Classifier: Operating System :: OS Independent
Classifier: Programming Language :: Python
Classifier: Programming Language :: Python :: 3.12
Classifier: Topic :: System :: Benchmark
Classifier: Topic :: System :: Hardware
Classifier: Topic :: Scientific/Engineering :: Artificial Intelligence
Requires-Python: >=3.10, <4
License-File: LICENSE
Requires-Dist: click==8.1.7
Requires-Dist: numpy==2.0.2
Requires-Dist: pillow==11.0.0
Requires-Dist: python-dotenv==1.0.1
Requires-Dist: soundfile==0.12.1
Requires-Dist: tensorflow==2.18.0
Requires-Dist: torch==2.4.1
Requires-Dist: transformers==4.46.2
Requires-Dist: tqdm==4.67.0
Dynamic: author
Dynamic: author-email
Dynamic: classifier
Dynamic: description
Dynamic: description-content-type
Dynamic: download-url
Dynamic: keywords
Dynamic: license
Dynamic: maintainer
Dynamic: maintainer-email
Dynamic: project-url
Dynamic: requires-dist
Dynamic: requires-python
Dynamic: summary
